{
   "core/sentence_input":{
      "name":"core/sentence_input",
      "description":"Marks the beginning of a translation workflow",
      "version":"v0.1",
      "icon":"keyboard-o",
      "inports":[

      ],
      "outports":[
         {
            "name":"out_ssf",
            "type":"all"
         }
      ],
      "metadata":{
         "label":"Sentence Input"
      }
   },
   "core/sentence_output":{
      "name":"core/sentence_output",
      "description":"Shows the output",
      "version":"v0.1",
      "icon":"desktop",
      "inports":[
         {
            "name":"in_ssf",
            "type":"all"
         }
      ],
      "outports":[

      ],
      "metadata":{
         "label":"Output"
      }
   }
}